{
  "page_id": "BLR-0425-PA-0042650::BLR-0425-PA-0042650_F-SHWETAPA_250428_0922@G.pdf_page_18::18",
  "patient_id": "BLR-0425-PA-0042650",
  "source_file": "BLR-0425-PA-0042650_F-SHWETAPA_250428_0922@G.pdf_page_18.png",
  "page_number": 18,
  "text": "‘(,9 SPANDANA\n\nHEART & SUPER SPECIALITY HOSPITAL\n\n \n\n \n \n\nLab No. 2‘ MRN : 05399 eonected Qn ‘us : 52 AM\n2 :or. PRAVEEN REDDY M.a.s.s V *\nE. ,1 B I E .\n\nSpecimen Test Description §esuWUnits Reference Range\nURINE . URINE OTHERS Nil Nil\n\nURINE . URINE BLOOD Absent Absent\n\nEnd pf Report\\———-\n\nDr. Geetha S\n(Ml-3BS,MD in Pathology)\n\nConsuitant Pathologist\nV\n\n \n \n \n \n\nConsultant Pathologist\n\n(A Unit of Spandana Health Sciences!\n206/343, Near Trhity Complex. Sornpura Gate, Sarjapura Man Ro_ad, Ban;Ioro—562125_\n\nI cbl'aheam1xiarmes.o0m \nToll-free Number: 7878",
  "document_type": "lab_report"
}